[
	{
		"question": "ကေလးရဲ႕ ခ်က္ၾကိဳးငုတ္တိုင္ဟာ  ဘယ္အခ်ိန္မွ ေၾကြက်မွာလည္း။",
		"answer": "ေမြးကင္းစကေလးငယ္ရဲ ႔ ခ်က္ၾကိဳးငုတ္တိုဟာ ေမြးျပီး ၁၀ ရက္မွ ရက္သတၱပတ္ အနည္းငယ္အတြင္း သူ ႔ဘာသာသူ ေၾကြက်သြားပါလိမ့္မယ္။ အလ်င္လိုျပီး ျမန္ျမန္ေၾကြက်ေအာင္မၾကိဳးစားပါနဲ႔။"

	},
	{
		"question": "လိင္အဂၤါနဲ႔ ရင္သားမ်ားအေၾကာင္း ရွင္းျပပါ။",
		"answer": "မိခင္ရဲ႕ေဟာ္မုန္းဓာတ္ဟာ ကေလးေမြးဖြားတဲ့အခ်ိန္မွာ အလြန္ျမင့္ေနတဲ့အတြက္ သားျဖစ္ေစ၊ သမီးျဖစ္ေစ ေမြးကင္းစကေလးရဲ႕ ရင္သားမ်ားနဲ႔ လိင္အဂၤါမ်ားဟာ ၾကီးထြားေနေလ့ရွိပါတယ္။ သမီးငယ္မ်ားရဲ႕ မိန္းမအဂၤါမွာ ေသြးအနည္းငယ္ ထြက္ေနတတ္တာလည္း ေတြ႕ရပါတယ္။ ဒါဟာ ပံုမွန္သဘာဝပါပဲ။ မၾကာခင္ ရပ္သြားပါလိမ့္မယ္။"
	},
	{
		"question": "ေမြးကင္းစအခ်န္မွာ ကေလးက အျမင္အာရံုကိုပဲ သင္ယူမႈရွိတာလားရွင့္။",
		"answer": "မဟုတ္ပါဘူး။ ကေလးငယ္ဟာ အထိအေတြ႕၊ အနံ႔၊ အျမင္နဲ႔ အသံ စတဲ့အာရံုေတြကို စတင္သင္ယူေနတာ ျဖစ္တယ္။"

	},
	{
		"question": "ေမြးေမြးျခင္း ကေလးရဲ႕ လက္မွာ အပူေလာင္ဖုေလးေတက ဘာလို႔ျဖစ္ရတာလဲ။",
		"answer": "မိခင္ရဲ႕ ဗိုက္ထဲမွာရွိေနစဥ္ ကေလးငယ္ေတြဟာ သူတို႔လက္မ၊ သို႔မဟုတ္ လက္ေခ်ာင္းေလးေတြကို ပါးစပ္နဲ႔ စုပ္ထားတက္တဲ့အတြက္ အသားမာတက္သလိုျဖစ္ျပီး တစ္ခါတရံ အပူေလာင္ဖုေလးေတြ ျဖစ္ေနတတ္တာပါ။"

	},
	{
		"question": "ခ်က္တုိင္ကို ဘယ္လုိထားရမလဲ။",
		"answer": "ခ်က္တိုင္ကို ေရာဂါပိုးမဝန္ေအာင္ ေျခာက္ေသြ႕ေနေအာင္ ထားရပါမယ္။ ခ်က္တိုင္ပြန္းပဲ့ျခင္းမွ ကာကြယ္ရန္အတြက္ အႏွီးစကၠဴ(Diaper)သံုးမယ္ဆိုရင္ ခ်က္တိုင္နဲ႔ထိမယ့္ေနရာမွာ အေပါက္ကေလး ေဖာက္ေပးထားသင့္ပါတယ္။ အႏွီးစကၠဴရဲ ႔ေရွ ႔ဘက္ျခမ္းကို ခ်က္တိုင္ရဲ ႔ေအာက္ဘက္မွာ ေခါက္ထားရင္လည္း ရပါတယ္။ အႏွီးပိတ္နဲ႔ ေထြးထားရင္လည္း ခ်က္တိုင္ကို မထိမိ၊ မဖိမိေအာင္ ထားသင့္ပါတယ္။ ခ်က္ၾကိဳးမွာ သာမန္ထက္ေသြးထြက္မ်ားေနျခင္း၊ ခ်က္တိုင္ ပတ္လည္မွာ အေရးျပားေတြ နီရဲေနျခင္း၊ ေရာင္ရမ္းေနျခင္းမ်ားေတြ ႔ရရင္ အနာရင္းျပီး ပိုးဝင္တာျဖစ္လို႔ ဆရာဝန္နဲ႔ျပသရာမွာ ျဖစ္ပါတယ္။"
	},
	{
		"question": "ေမြးေမြးျခင္း ကေလးရဲ႕ မ်က္ႏွာက ျပာႏွမ္း၊ ေရာင္ရမ္းေနပါတယ္။ စိုးရိမ္ရလား။",
		"answer": ""
	}

]
